psychopy_eyetracker_eyelogic/__init__.py
psychopy_eyetracker_eyelogic/eyelogic/__init__.py
psychopy_eyetracker_eyelogic/eyelogic/psychopy/__init__.py
psychopy_eyetracker_eyelogic/eyelogic/psychopy/calibration.py
psychopy_eyetracker_eyelogic/eyelogic/psychopy/default_eyetracker.yaml
psychopy_eyetracker_eyelogic/eyelogic/psychopy/eyetracker.py
psychopy_eyetracker_eyelogic/eyelogic/psychopy/supported_config_settings.yaml
psychopy_eyetracker_eyelogic-1.2.0.dist-info/licenses/LICENSE
psychopy_eyetracker_eyelogic-1.2.0.dist-info/METADATA
psychopy_eyetracker_eyelogic-1.2.0.dist-info/WHEEL
psychopy_eyetracker_eyelogic-1.2.0.dist-info/entry_points.txt
psychopy_eyetracker_eyelogic-1.2.0.dist-info/top_level.txt
psychopy_eyetracker_eyelogic-1.2.0.dist-info/RECORD
