Metadata-Version: 2.4
Name: psychopy-eyetracker-eyelogic
Version: 1.2.0
Summary: extension package for PsychoPy which adds support for EyeLogic eyetrackers to ioHub
Author-email: EyeLogic GmbH <info@eyelogicsolutions.com>
License: Freely Distributable
Classifier: License :: Freely Distributable
Classifier: Programming Language :: Python :: 3
Classifier: Programming Language :: Python :: 3 :: Only
Classifier: Programming Language :: Python :: 3.7
Classifier: Programming Language :: Python :: 3.8
Classifier: Programming Language :: Python :: 3.9
Classifier: Programming Language :: Python :: 3.10
Classifier: Programming Language :: Python :: 3.11
Classifier: Programming Language :: Python :: Implementation :: CPython
Requires-Python: >=3.7
License-File: LICENSE
Requires-Dist: eyelogic-sdk
Dynamic: license-file
